{
  "status" : 1,
  "data" : [ {
    "id" : "M0000000000000",
    "name" : "0",
    "funcId" : "0",
    "icon" : "0",
    "isvisible" : "N",
    "isenable" : "0",
    "isVirtualNode" : "0",
    "parentId" : "0",
    "classify" : "0",
    "layoutId" : "0",
    "sort" : 0,
    "createTime" : 1469426520000,
    "version" : 0,
    "tenantId" : "n2cnwzbl",
    "label" : "",
    "system" : ""
  }, {
    "id" : "M0000000000001",
    "name" : "用户信息",
    "funcId" : "#school_user/user",
    "icon" : "fa-laptop",
    "isvisible" : "Y",
    "isenable" : "Y",
    "isVirtualNode" : "N",
    "parentId" : "M0000000000000",
    "classify" : "",
    "layoutId" : "#school_user/user",
    "sort" : 1,
    "createTime" : 1469427892000,
    "version" : 0,
    "tenantId" : "n2cnwzbl",
    "label" : "",
    "system" : ""
  }, {
    "id" : "M0000000000002",
    "name" : "学生信息",
    "funcId" : "#school_student/student",
    "icon" : "fa-user",
    "isvisible" : "Y",
    "isenable" : "Y",
    "isVirtualNode" : "N",
    "parentId" : "M0000000000000",
    "classify" : "",
    "layoutId" : "#school_student/student",
    "sort" : 2,
    "createTime" : 1469428034000,
    "version" : 0,
    "tenantId" : "n2cnwzbl",
    "label" : "",
    "system" : ""
  }, {
    "id" : "M0000000000004",
    "name" : "教师信息",
    "funcId" : "#school_teacher/teacher",
    "icon" : "fa-user",
    "isvisible" : "Y",
    "isenable" : "Y",
    "isVirtualNode" : "N",
    "parentId" : "M0000000000000",
    "classify" : "",
    "layoutId" : "#school_teacher/teacher",
    "sort" : 3,
    "createTime" : 1469426915000,
    "version" : 0,
    "tenantId" : "n2cnwzbl",
    "label" : "",
    "system" : ""
  }, {
    "id" : "M0000000000005",
    "name" : "班级信息",
    "funcId" : "#school_class/class",
    "icon" : "fa-group",
    "isvisible" : "Y",
    "isenable" : "Y",
    "isVirtualNode" : "N",
    "parentId" : "M0000000000000",
    "classify" : "",
    "layoutId" : "#school_class/class",
    "sort" : 4,
    "createTime" : 1469426915000,
    "version" : 0,
    "tenantId" : "n2cnwzbl",
    "label" : "",
    "system" : ""
  }, {
    "id" : "M0000000000008",
    "name" : "课程信息",
    "funcId" : "#school_course/course",
    "icon" : "icon-application",
    "isvisible" : "Y",
    "isenable" : "Y",
    "isVirtualNode" : "N",
    "parentId" : "M0000000000000",
    "classify" : "",
    "layoutId" : "#school_course/course",
    "sort" : 5,
    "createTime" : 1469426915000,
    "version" : 0,
    "tenantId" : "n2cnwzbl",
    "label" : "",
    "system" : ""
  }, {
    "id" : "M0000000000010",
    "name" : "课表分配信息",
    "funcId" : "#school_classcourse/classcourse",
    "icon" : "icon-xiaobujianshouquan",
    "isvisible" : "Y",
    "isenable" : "Y",
    "isVirtualNode" : "N",
    "parentId" : "M0000000000000",
    "classify" : "",
    "layoutId" : "#school_classcourse/classcourse",
    "sort" : 6,
    "createTime" : 1469426915000,
    "version" : 0,
    "tenantId" : "n2cnwzbl",
    "label" : "",
    "system" : ""
  }, {
    "id" : "M0000000000011",
    "name" : "订单管理",
    "funcId" : "#test_order/order",
    "icon" : "icon-smallauthorization",
    "isvisible" : "Y",
    "isenable" : "Y",
    "isVirtualNode" : "N",
    "parentId" : "M0000000000000",
    "classify" : "",
    "layoutId" : "#test_order/order",
    "sort" : 7,
    "createTime" : 1469426915000,
    "version" : 0,
    "tenantId" : "n2cnwzbl",
    "label" : "",
    "system" : ""
  }, {
    "id" : "M0000000000012",
    "name" : "测试项目维护",
    "funcId" : "#test_item/testitem",
    "icon" : "icon-icon4",
    "isvisible" : "Y",
    "isenable" : "Y",
    "isVirtualNode" : "N",
    "parentId" : "M0000000000000",
    "classify" : "",
    "layoutId" : "#test_item/testitem",
    "sort" : 8,
    "createTime" : 1469426915000,
    "version" : 0,
    "tenantId" : "n2cnwzbl",
    "label" : "",
    "system" : ""
  }, {
    "id" : "M0000000000025",
    "name" : "产品管理",
    "funcId" : "#goods/page",
    "icon" : "icon-thewidget",
    "isvisible" : "Y",
    "isenable" : "Y",
    "isVirtualNode" : "N",
    "parentId" : "M0000000000000",
    "classify" : "",
    "layoutId" : "#goods/page",
    "sort" : 16,
    "createTime" : 1469426915000,
    "version" : 0,
    "tenantId" : "n2cnwzbl",
    "label" : "",
    "system" : ""
  }],
  "msg" : "操作成功！"
}
